ngautonml_image/__init__.py
ngautonml_image/algorithms/__init__.py
ngautonml_image/algorithms/sequential.py
ngautonml_image/algorithms/sequential_test.py
ngautonml_image/data_loaders/__init__.py
ngautonml_image/data_loaders/image_tensor_data_loader.py
ngautonml_image/data_loaders/image_tensor_data_loader_test.py
ngautonml_image/data_loaders/impl/__init__.py
ngautonml_image/data_loaders/impl/image_tensor_params.py
ngautonml_image/data_loaders/impl/image_tensor_params_test.py
ngautonml_image/examples_test.py
ngautonml_image/py.typed
ngautonml_image/requirements-dev.txt
ngautonml_image/requirements.txt
ngautonml_image/splitters/__init__.py
ngautonml_image/splitters/nop_splitter.py
ngautonml_image/splitters/tf_splitter.formerlypy
ngautonml_image/templates/__init__.py
ngautonml_image/templates/image_clf.py
ngautonml_image-0.58b8.dist-info/METADATA
ngautonml_image-0.58b8.dist-info/WHEEL
ngautonml_image-0.58b8.dist-info/entry_points.txt
ngautonml_image-0.58b8.dist-info/RECORD
