Metadata-Version: 2.3
Name: ngautonml_image
Version: 0.58b8
Summary: a plugin that installs image processing tools for ngAutonML
Keywords: machine learning,image processing
Author: L.H. Piggy Yarroll
Author-email: piggy@acm.org
Classifier: Development Status :: 4 - Beta
Classifier: Intended Audience :: Science/Research
Classifier: Topic :: Scientific/Engineering :: Artificial Intelligence
Classifier: Typing :: Typed
